pyei/__init__.py
pyei/data.py
pyei/distribution_utils.py
pyei/goodmans_er.py
pyei/greiner_quinn_gibbs_sampling.py
pyei/io_utils.py
pyei/plot_utils.py
pyei/r_by_c.py
pyei/r_by_c_models.py
pyei/r_by_c_utils.py
pyei/two_by_two.py
pyei-1.1.4.dist-info/licenses/LICENSE
pyei-1.1.4.dist-info/METADATA
pyei-1.1.4.dist-info/WHEEL
pyei-1.1.4.dist-info/top_level.txt
pyei-1.1.4.dist-info/RECORD
