Metadata-Version: 2.4
Name: pyei
Version: 1.1.4
Home-page: https://github.com/mggg/ecological-inference
Author: Metric Geometry and Gerrymandering Group
License-File: LICENSE
Requires-Dist: pymc>=5.21.0
Requires-Dist: arviz
Requires-Dist: scikit-learn
Requires-Dist: matplotlib
Requires-Dist: pandas
Requires-Dist: seaborn
Requires-Dist: graphviz
Requires-Dist: numpy
Requires-Dist: jax
Requires-Dist: numpyro
Requires-Dist: jaxlib
Requires-Dist: numba
Requires-Dist: netCDF4
Dynamic: author
Dynamic: description
Dynamic: description-content-type
Dynamic: home-page
Dynamic: license-file
Dynamic: requires-dist
